DESCRIPTION.rst
MANIFEST.in
setup.cfg
setup.py
sl2gtfs/__init__.py
sl2gtfs/mapper.py
sl2gtfs.egg-info/PKG-INFO
sl2gtfs.egg-info/SOURCES.txt
sl2gtfs.egg-info/dependency_links.txt
sl2gtfs.egg-info/entry_points.txt
sl2gtfs.egg-info/requires.txt
sl2gtfs.egg-info/top_level.txt