Metadata-Version: 1.1
Name: sl2gtfs
Version: 1.0.1
Summary: Converts SL stop ids to GTFS stop ids
Home-page: https://github.com/johannilsson/sl2gtfs
Author: Johan Nilsson
Author-email: johan@markupartist.com
License: MIT
Keywords: gtfs stockholm
Platform: UNKNOWN
Classifier: Development Status :: 3 - Alpha
Classifier: Intended Audience :: Developers
Classifier: Topic :: Software Development :: Build Tools
Classifier: License :: OSI Approved :: MIT License
Classifier: Programming Language :: Python :: 2
Classifier: Programming Language :: Python :: 3
